{"version":1,"resource":"vscode-userdata:/home/karan/.config/Code/User/settings.json","entries":[{"id":"HTJS.json","timestamp":1676297370277},{"id":"ofJf.json","timestamp":1676297541810},{"id":"OLnZ.json","timestamp":1676297556548},{"id":"mCj1.json","timestamp":1676443348056},{"id":"hA89.json","timestamp":1676443364166},{"id":"ZxQl.json","timestamp":1676443387635},{"id":"WugE.json","timestamp":1676443437555},{"id":"2eb6.json","timestamp":1676443473835},{"id":"Teiy.json","timestamp":1676470739817},{"id":"9169.json","timestamp":1676470846586},{"id":"iCxa.json","timestamp":1676470906736},{"id":"dONX.json","timestamp":1676745672804},{"id":"RHmo.json","timestamp":1676891956025}]}