{"version":1,"resource":"file:///home/karan/waste/STT2colabration/Assignment2/q6/q6_b","entries":[{"id":"lOFL","timestamp":1677230045109},{"id":"ZAEe","timestamp":1677231749996},{"id":"v77F","timestamp":1677231777462},{"id":"7jPL","timestamp":1677231796914},{"id":"5yDC","timestamp":1677231850452},{"id":"eukR","timestamp":1677231873131},{"id":"Jx2u","timestamp":1677231913770},{"id":"X3hy","timestamp":1677231963554},{"id":"6bVk","timestamp":1677231975527},{"id":"puEh","timestamp":1677232024695},{"id":"fTJH","timestamp":1677232429092},{"id":"GfCQ","timestamp":1677232442458},{"id":"PK0A","timestamp":1677232587849},{"id":"vAu8","source":"undoRedo.source","timestamp":1677232591452},{"id":"hp47","source":"undoRedo.source","timestamp":1677232606485},{"id":"CNa7","timestamp":1677232644370},{"id":"c1nK","timestamp":1677232664696},{"id":"Otrm","timestamp":1677232698951},{"id":"RvIg","timestamp":1677232717244},{"id":"qygk","timestamp":1677232740226},{"id":"c8PF","timestamp":1677232757762}]}